udp_over_tls_pool/__init__.py
udp_over_tls_pool/asdnotify.py
udp_over_tls_pool/client.py
udp_over_tls_pool/client_session.py
udp_over_tls_pool/constants.py
udp_over_tls_pool/dgram_upstream.py
udp_over_tls_pool/server.py
udp_over_tls_pool/session_dispatcher.py
udp_over_tls_pool/stream_listener.py
udp_over_tls_pool/udp_listener.py
udp_over_tls_pool/upstream.py
udp_over_tls_pool/utils.py
udp_over_tls_pool-0.1.1.dist-info/LICENSE
udp_over_tls_pool-0.1.1.dist-info/METADATA
udp_over_tls_pool-0.1.1.dist-info/WHEEL
udp_over_tls_pool-0.1.1.dist-info/entry_points.txt
udp_over_tls_pool-0.1.1.dist-info/top_level.txt
udp_over_tls_pool-0.1.1.dist-info/zip-safe
udp_over_tls_pool-0.1.1.dist-info/RECORD
