Metadata-Version: 2.1
Name: udp-over-tls-pool
Version: 0.1.1
Summary: Network wrapper which transports UDP packets over multiple TLS sessions
Home-page: https://github.com/Snawoot/udp-over-tls-pool
Author: Vladislav Yarmak
Author-email: vladislav-ex-src@vm-0.com
License: MIT
Platform: UNKNOWN
Classifier: Programming Language :: Python :: 3.5
Classifier: License :: OSI Approved :: MIT License
Classifier: Operating System :: OS Independent
Classifier: Development Status :: 3 - Alpha
Classifier: Environment :: No Input/Output (Daemon)
Classifier: Intended Audience :: End Users/Desktop
Classifier: Intended Audience :: Information Technology
Classifier: Intended Audience :: Telecommunications Industry
Classifier: Intended Audience :: System Administrators
Classifier: Natural Language :: English
Classifier: Topic :: Internet
Classifier: Topic :: Security
Requires-Python: >=3.5.3
